CHANGES.txt
LICENSE.txt
MANIFEST.in
README.rst
setup.cfg
setup.py
chartbeatpy/__init__.py
chartbeatpy.egg-info/PKG-INFO
chartbeatpy.egg-info/SOURCES.txt
chartbeatpy.egg-info/dependency_links.txt
chartbeatpy.egg-info/requires.txt
chartbeatpy.egg-info/top_level.txt
docs/AUTHORS.rst