Metadata-Version: 1.1
Name: chartbeatpy
Version: 0.2.1
Summary: A charbeat API wrapper.
Home-page: https://github.com/detroit-media-partnership/chartbeatpy
Author: Timothée Peignier
Author-email: timothee.peignier@tryphon.org
License: LICENSE.rst
Keywords: chartbeat,API
Platform: UNKNOWN
Classifier: Development Status :: 4 - Beta
Classifier: Intended Audience :: Developers
Classifier: License :: OSI Approved :: MIT License
Classifier: Operating System :: OS Independent
Classifier: Programming Language :: Python
Classifier: Programming Language :: Python :: 3
Classifier: Topic :: Utilities
